[
    {
        "root_name": "e",
        "root_id": "e1",
        "second": "fsgb1",
        "minor_third": "g1",
        "third": "gsab1",
        "fourth": "a1",
        "fifth": "b1",
        "flat_fifth": "asbb1",
        "sharp_fifth": "c1",
        "sixth": "csdb1",
        "minor_seventh": "d1",
        "major_seventh": "dseb1",
        "octive": "e2",
        "ninth": "fsgb2",
        "sharp_ninth": "g2",
        "eleventh": "a2",
        "thirteenth": "csdb2"
    },
    {
        "root_name": "e",
        "root_id": "e2",
        "second": "fsgb2",
        "minor_third": "g2",
        "third": "gsab2",
        "fourth": "a2",
        "fifth": "b2",
        "flat_fifth": "asbb2",
        "sharp_fifth": "c2",
        "sixth": "csdb2",
        "minor_seventh": "d2",
        "major_seventh": "dseb2",
        "octive": "e3",
        "ninth": "fsgb3",
        "sharp_ninth": "g3",
        "eleventh": "a3",
        "thirteenth": "csdb3"
    },
    {
        "root_name": "e",
        "root_id": "e3",
        "second": "fsgb3",
        "minor_third": "g3",
        "third": "gsab3",
        "fourth": "a3",
        "fifth": "b3",
        "flat_fifth": "asbb3",
        "sharp_fifth": "c3",
        "sixth": "csdb3",
        "minor_seventh": "d3",
        "major_seventh": "dseb3",
        "octive": "e4",
        "ninth": "0",
        "sharp_ninth": "0",
        "eleventh": "0",
        "thirteenth": "0"
    },
    {
        "root_name": "e",
        "root_id": "e4",
        "second": "0",
        "minor_third": "0",
        "third": "0",
        "fourth": "0",
        "fifth": "0",
        "flat_fifth": "0",
        "sharp_fifth": "0",
        "sixth": "0",
        "minor_seventh": "0",
        "major_seventh": "0",
        "octive": "0",
        "ninth": "0",
        "sharp_ninth": "0",
        "eleventh": "0",
        "thirteenth": "0"
    },
    {
        "root_name": "f",
        "root_id": "f1",
        "second": "g1",
        "minor_third": "gsab1",
        "third": "a1",
        "fourth": "asbb1",
        "fifth": "c1",
        "flat_fifth": "b1",
        "sharp_fifth": "csdb1",
        "sixth": "d1",
        "minor_seventh": "dseb1",
        "major_seventh": "e2",
        "octive": "f2",
        "ninth": "g2",
        "sharp_ninth": "gsab2",
        "eleventh": "asbb2",
        "thirteenth": "d2"
    },
    {
        "root_name": "f",
        "root_id": "f2",
        "second": "g2",
        "minor_third": "gsab2",
        "third": "a2",
        "fourth": "asbb2",
        "fifth": "c2",
        "flat_fifth": "b2",
        "sharp_fifth": "csdb2",
        "sixth": "d2",
        "minor_seventh": "dseb2",
        "major_seventh": "e3",
        "octive": "f3",
        "ninth": "g3",
        "sharp_ninth": "gsab3",
        "eleventh": "asbb3",
        "thirteenth": "d3"
    },
    {
        "root_name": "f",
        "root_id": "f3",
        "second": "g3",
        "minor_third": "gsab3",
        "third": "a3",
        "fourth": "asbb3",
        "fifth": "c3",
        "flat_fifth": "b3",
        "sharp_fifth": "csdb3",
        "sixth": "d3",
        "minor_seventh": "dseb3",
        "major_seventh": "e4",
        "octive": "0",
        "ninth": "0",
        "sharp_ninth": "0",
        "eleventh": "0",
        "thirteenth": "0"
    },
    {
        "root_name": "fsgb",
        "root_id": "fsgb1",
        "second": "gsab1",
        "minor_third": "a1",
        "third": "asbb1",
        "fourth": "b1",
        "fifth": "csdb1",
        "flat_fifth": "c1",
        "sharp_fifth": "d1",
        "sixth": "dseb1",
        "minor_seventh": "e2",
        "major_seventh": "f1",
        "octive": "fsgb2",
        "ninth": "gsab2",
        "sharp_ninth": "a2",
        "eleventh": "b2",
        "thirteenth": "dseb2"
    },
    {
        "root_name": "fsgb",
        "root_id": "fsgb2",
        "second": "gsab2",
        "minor_third": "a2",
        "third": "asbb2",
        "fourth": "b2",
        "fifth": "csdb2",
        "flat_fifth": "c2",
        "sharp_fifth": "d2",
        "sixth": "dseb2",
        "minor_seventh": "e3",
        "major_seventh": "f2",
        "octive": "fsgb3",
        "ninth": "gsab3",
        "sharp_ninth": "a3",
        "eleventh": "b3",
        "thirteenth": "dseb3"
    },
    {
        "root_name": "fsgb",
        "root_id": "fsgb3",
        "second": "gsab3",
        "minor_third": "a3",
        "third": "asbb3",
        "fourth": "b3",
        "fifth": "csdb3",
        "flat_fifth": "c3",
        "sharp_fifth": "d3",
        "sixth": "dseb3",
        "minor_seventh": "e4",
        "major_seventh": "f3",
        "octive": "0",
        "ninth": "0",
        "sharp_ninth": "0",
        "eleventh": "0",
        "thirteenth": "0"
    },
    {
        "root_name": "g",
        "root_id": "g1",
        "second": "a1",
        "minor_third": "asbb1",
        "third": "b1",
        "fourth": "c1",
        "fifth": "d1",
        "flat_fifth": "csdb1",
        "sharp_fifth": "dseb1",
        "sixth": "e2",
        "minor_seventh": "f2",
        "major_seventh": "fsgb2",
        "octive": "g2",
        "ninth": "a2",
        "sharp_ninth": "asbb2",
        "eleventh": "c2",
        "thirteenth": "e3"
    },
    {
        "root_name": "g",
        "root_id": "g2",
        "second": "a2",
        "minor_third": "asbb2",
        "third": "b2",
        "fourth": "c2",
        "fifth": "d2",
        "flat_fifth": "csdb2",
        "sharp_fifth": "dseb2",
        "sixth": "e3",
        "minor_seventh": "f3",
        "major_seventh": "fsgb3",
        "octive": "g3",
        "ninth": "a3",
        "sharp_ninth": "asbb3",
        "eleventh": "c3",
        "thirteenth": "e4"
    },
    {
        "root_name": "g",
        "root_id": "g3",
        "second": "a3",
        "minor_third": "asbb3",
        "third": "b3",
        "fourth": "c3",
        "fifth": "d3",
        "flat_fifth": "csdb3",
        "sharp_fifth": "dseb3",
        "sixth": "e4",
        "minor_seventh": "0",
        "major_seventh": "0",
        "octive": "0",
        "ninth": "0",
        "sharp_ninth": "0",
        "eleventh": "0",
        "thirteenth": "0"
    },
    {
        "root_name": "gsab",
        "root_id": "gsab1",
        "second": "asbb1",
        "minor_third": "b1",
        "third": "c1",
        "fourth": "csdb1",
        "fifth": "dseb1",
        "flat_fifth": "d1",
        "sharp_fifth": "e2",
        "sixth": "f1",
        "minor_seventh": "fsgb1",
        "major_seventh": "g1",
        "octive": "gsab2",
        "ninth": "asbb2",
        "sharp_ninth": "b2",
        "eleventh": "csdb2",
        "thirteenth": "dseb2"
    },
    {
        "root_name": "gsab",
        "root_id": "gsab2",
        "second": "asbb2",
        "minor_third": "b2",
        "third": "c2",
        "fourth": "csdb2",
        "fifth": "dseb2",
        "flat_fifth": "d2",
        "sharp_fifth": "e3",
        "sixth": "f2",
        "minor_seventh": "fsgb2",
        "major_seventh": "g2",
        "octive": "gsab3",
        "ninth": "asbb3",
        "sharp_ninth": "b3",
        "eleventh": "csdb3",
        "thirteenth": "dseb3"
    },
    {
        "root_name": "gsab",
        "root_id": "gsab3",
        "second": "asbb3",
        "minor_third": "b3",
        "third": "c3",
        "fourth": "csdb3",
        "fifth": "dseb3",
        "flat_fifth": "d3",
        "sharp_fifth": "e4",
        "sixth": "f3",
        "minor_seventh": "fsgb3",
        "major_seventh": "g3",
        "octive": "0",
        "ninth": "0",
        "sharp_ninth": "0",
        "eleventh": "0",
        "thirteenth": "0"
    },
    {
        "root_name": "a",
        "root_id": "a1",
        "second": "b1",
        "minor_third": "c1",
        "third": "csdb1",
        "fourth": "d1",
        "fifth": "e2",
        "flat_fifth": "dseb1",
        "sharp_fifth": "f2",
        "sixth": "fsgb2",
        "minor_seventh": "g2",
        "major_seventh": "gsab2",
        "octive": "a2",
        "ninth": "b2",
        "sharp_ninth": "c2",
        "eleventh": "d2",
        "thirteenth": "fsgb3"
    },
    {
        "root_name": "a",
        "root_id": "a2",
        "second": "b2",
        "minor_third": "c2",
        "third": "csdb2",
        "fourth": "d2",
        "fifth": "e3",
        "flat_fifth": "dseb2",
        "sharp_fifth": "f3",
        "sixth": "fsgb3",
        "minor_seventh": "g3",
        "major_seventh": "gsab3",
        "octive": "a3",
        "ninth": "b3",
        "sharp_ninth": "c3",
        "eleventh": "d3",
        "thirteenth": "0"
    },
    {
        "root_name": "a",
        "root_id": "a3",
        "second": "b3",
        "minor_third": "c3",
        "third": "csdb3",
        "fourth": "d3",
        "fifth": "e4",
        "flat_fifth": "dseb3",
        "sharp_fifth": "0",
        "sixth": "0",
        "minor_seventh": "0",
        "major_seventh": "0",
        "octive": "0",
        "ninth": "0",
        "sharp_ninth": "0",
        "eleventh": "0",
        "thirteenth": "0"
    },
    {
        "root_name": "asbb",
        "root_id": "asbb1",
        "second": "c1",
        "minor_third": "csdb1",
        "third": "d1",
        "fourth": "dseb1",
        "fifth": "f2",
        "flat_fifth": "e2",
        "sharp_fifth": "fsgb2",
        "sixth": "g2",
        "minor_seventh": "gsab2",
        "major_seventh": "a2",
        "octive": "asbb2",
        "ninth": "c2",
        "sharp_ninth": "csdb2",
        "eleventh": "dseb2",
        "thirteenth": "g3"
    },
    {
        "root_name": "asbb",
        "root_id": "asbb2",
        "second": "c2",
        "minor_third": "csdb2",
        "third": "d2",
        "fourth": "dseb2",
        "fifth": "f3",
        "flat_fifth": "e3",
        "sharp_fifth": "fsgb3",
        "sixth": "g3",
        "minor_seventh": "gsab3",
        "major_seventh": "a3",
        "octive": "asbb3",
        "ninth": "c3",
        "sharp_ninth": "csdb3",
        "eleventh": "dseb3",
        "thirteenth": "0"
    },
    {
        "root_name": "asbb",
        "root_id": "asbb3",
        "second": "c3",
        "minor_third": "csdb3",
        "third": "d3",
        "fourth": "dseb3",
        "fifth": "0",
        "flat_fifth": "e4",
        "sharp_fifth": "0",
        "sixth": "0",
        "minor_seventh": "0",
        "major_seventh": "0",
        "octive": "0",
        "ninth": "0",
        "sharp_ninth": "0",
        "eleventh": "0",
        "thirteenth": "0"
    },
    {
        "root_name": "b",
        "root_id": "b1",
        "second": "csdb1",
        "minor_third": "d1",
        "third": "dseb1",
        "fourth": "e2",
        "fifth": "fsgb2",
        "flat_fifth": "f2",
        "sharp_fifth": "g2",
        "sixth": "gsab2",
        "minor_seventh": "a2",
        "major_seventh": "asbb2",
        "octive": "b2",
        "ninth": "csdb2",
        "sharp_ninth": "d2",
        "eleventh": "e3",
        "thirteenth": "gsab3"
    },
    {
        "root_name": "b",
        "root_id": "b2",
        "second": "csdb2",
        "minor_third": "d2",
        "third": "dseb2",
        "fourth": "e3",
        "fifth": "fsgb3",
        "flat_fifth": "f3",
        "sharp_fifth": "g3",
        "sixth": "gsab3",
        "minor_seventh": "a3",
        "major_seventh": "asbb3",
        "octive": "b3",
        "ninth": "csdb3",
        "sharp_ninth": "d3",
        "eleventh": "e4",
        "thirteenth": "0"
    },
    {
        "root_name": "b",
        "root_id": "b3",
        "second": "csdb3",
        "minor_third": "d3",
        "third": "dseb3",
        "fourth": "e4",
        "fifth": "0",
        "flat_fifth": "0",
        "sharp_fifth": "0",
        "sixth": "0",
        "minor_seventh": "0",
        "major_seventh": "asbb0",
        "octive": "0",
        "ninth": "0",
        "sharp_ninth": "0",
        "eleventh": "0",
        "thirteenth": "0"
    },
    {
        "root_name": "c",
        "root_id": "c1",
        "second": "d1",
        "minor_third": "dseb1",
        "third": "e2",
        "fourth": "f1",
        "fifth": "g1",
        "flat_fifth": "fsgb1",
        "sharp_fifth": "gsab1",
        "sixth": "a1",
        "minor_seventh": "asbb1",
        "major_seventh": "b1",
        "octive": "c2",
        "ninth": "d2",
        "sharp_ninth": "dseb2",
        "eleventh": "f2",
        "thirteenth": "a2"
    },
    {
        "root_name": "c",
        "root_id": "c2",
        "second": "d2",
        "minor_third": "dseb2",
        "third": "e3",
        "fourth": "f2",
        "fifth": "g2",
        "flat_fifth": "fsgb2",
        "sharp_fifth": "gsab2",
        "sixth": "a2",
        "minor_seventh": "asbb2",
        "major_seventh": "b2",
        "octive": "c3",
        "ninth": "d3",
        "sharp_ninth": "dseb3",
        "eleventh": "f3",
        "thirteenth": "a3"
    },
    {
        "root_name": "c",
        "root_id": "c3",
        "second": "d3",
        "minor_third": "dseb3",
        "third": "e4",
        "fourth": "f3",
        "fifth": "g3",
        "flat_fifth": "fsgb3",
        "sharp_fifth": "gsab3",
        "sixth": "a3",
        "minor_seventh": "asbb3",
        "major_seventh": "b3",
        "octive": "0",
        "ninth": "0",
        "sharp_ninth": "0",
        "eleventh": "0",
        "thirteenth": "0"
    },
    {
        "root_name": "csdb",
        "root_id": "csdb1",
        "second": "dseb1",
        "minor_third": "e2",
        "third": "f1",
        "fourth": "fsgb1",
        "fifth": "gsab1",
        "flat_fifth": "g1",
        "sharp_fifth": "a1",
        "sixth": "asbb1",
        "minor_seventh": "b1",
        "major_seventh": "c1",
        "octive": "csdb2",
        "ninth": "dseb2",
        "sharp_ninth": "e3",
        "eleventh": "fsgb2",
        "thirteenth": "asbb2"
    },
    {
        "root_name": "csdb",
        "root_id": "csdb2",
        "second": "dseb2",
        "minor_third": "e3",
        "third": "f2",
        "fourth": "fsgb2",
        "fifth": "gsab2",
        "flat_fifth": "g2",
        "sharp_fifth": "a2",
        "sixth": "asbb2",
        "minor_seventh": "b2",
        "major_seventh": "c2",
        "octive": "csdb3",
        "ninth": "dseb3",
        "sharp_ninth": "e4",
        "eleventh": "fsgb3",
        "thirteenth": "asbb3"
    },
    {
        "root_name": "csdb",
        "root_id": "csdb3",
        "second": "dseb3",
        "minor_third": "e4",
        "third": "f3",
        "fourth": "fsgb3",
        "fifth": "gsab3",
        "flat_fifth": "g3",
        "sharp_fifth": "a3",
        "sixth": "asbb3",
        "minor_seventh": "b3",
        "major_seventh": "c3",
        "octive": "0",
        "ninth": "0",
        "sharp_ninth": "0",
        "eleventh": "0",
        "thirteenth": "0"
    },
    {
        "root_name": "d",
        "root_id": "d1",
        "second": "e2",
        "minor_third": "f2",
        "third": "fsgb2",
        "fourth": "g2",
        "fifth": "a2",
        "flat_fifth": "gsab2",
        "sharp_fifth": "asbb2",
        "sixth": "b2",
        "minor_seventh": "c2",
        "major_seventh": "csdb2",
        "octive": "d2",
        "ninth": "e3",
        "sharp_ninth": "f3",
        "eleventh": "g3",
        "thirteenth": "b3"
    },
    {
        "root_name": "d",
        "root_id": "d2",
        "second": "e3",
        "minor_third": "f3",
        "third": "fsgb3",
        "fourth": "g3",
        "fifth": "a3",
        "flat_fifth": "gsab3",
        "sharp_fifth": "asbb3",
        "sixth": "b3",
        "minor_seventh": "c3",
        "major_seventh": "csdb3",
        "octive": "d3",
        "ninth": "e4",
        "sharp_ninth": "0",
        "eleventh": "0",
        "thirteenth": "0"
    },
    {
        "root_name": "d",
        "root_id": "d3",
        "second": "e4",
        "minor_third": "0",
        "third": "0",
        "fourth": "0",
        "fifth": "0",
        "flat_fifth": "0",
        "sharp_fifth": "0",
        "sixth": "0",
        "minor_seventh": "0",
        "major_seventh": "0",
        "octive": "0",
        "ninth": "0",
        "sharp_ninth": "0",
        "eleventh": "0",
        "thirteenth": "0"
    },
    {
        "root_name": "dseb",
        "root_id": "dseb1",
        "second": "f2",
        "minor_third": "fsgb2",
        "third": "g2",
        "fourth": "gsab2",
        "fifth": "asbb2",
        "flat_fifth": "a2",
        "sharp_fifth": "b2",
        "sixth": "c2",
        "minor_seventh": "csdb2",
        "major_seventh": "d2",
        "octive": "dseb2",
        "ninth": "f3",
        "sharp_ninth": "fsgb3",
        "eleventh": "gsab3",
        "thirteenth": "c3"
    },
    {
        "root_name": "dseb",
        "root_id": "dseb2",
        "second": "f3",
        "minor_third": "fsgb3",
        "third": "g3",
        "fourth": "gsab3",
        "fifth": "asbb3",
        "flat_fifth": "a3",
        "sharp_fifth": "b3",
        "sixth": "c3",
        "minor_seventh": "csdb3",
        "major_seventh": "d3",
        "octive": "dseb3",
        "ninth": "0",
        "sharp_ninth": "0",
        "eleventh": "0",
        "thirteenth": "0"
    },
    {
        "root_name": "dseb",
        "root_id": "dseb3",
        "second": "0",
        "minor_third": "0",
        "third": "0",
        "fourth": "0",
        "fifth": "0",
        "flat_fifth": "0",
        "sharp_fifth": "0",
        "sixth": "0",
        "minor_seventh": "0",
        "major_seventh": "0",
        "octive": "0",
        "ninth": "0",
        "sharp_ninth": "0",
        "eleventh": "0",
        "thirteenth": "0"
    }
]